kittrans/__init__.cpython-37m-darwin.so
kittrans/main.py
kittrans/models.cpython-37m-darwin.so
kittrans/urls.cpython-37m-darwin.so
tests/__init__.py
tests/test_login.py
kittrans-0.1.10.dist-info/METADATA
kittrans-0.1.10.dist-info/WHEEL
kittrans-0.1.10.dist-info/top_level.txt
kittrans-0.1.10.dist-info/RECORD
