Metadata-Version: 2.1
Name: kittrans
Version: 0.1.10
Summary: UNKNOWN
Home-page: UNKNOWN
License: UNKNOWN
Platform: UNKNOWN
Requires-Dist: requests
